macrometa_target_collection/__init__.py
macrometa_target_collection/main.py
macrometa_target_collection-1.0.2.dist-info/entry_points.txt
macrometa_target_collection-1.0.2.dist-info/LICENSE
macrometa_target_collection-1.0.2.dist-info/WHEEL
macrometa_target_collection-1.0.2.dist-info/METADATA
macrometa_target_collection-1.0.2.dist-info/RECORD
